{
  "R0_StudyID": {
    "all": [
      "StudyID"
    ]
  },
  "R0_CosmeticOther_Surgery": {
    "all": [
      "Q7_9_1_1",
      "brsurg2",
      "brsurg3",
      "brsurg4"
    ],
    "1": [
      "Q7_9_1_1"
    ],
    "2": [
      "brsurg2"
    ],
    "3": [
      "brsurg3"
    ],
    "4": [
      "brsurg4"
    ]
  },
  "R0_CosmeticOther_Hosp": {
    "all": [
      "Q7_9_2",
      "brsurghosp2",
      "brsurghosp3",
      "brsurghosp4"
    ],
    "1": [
      "Q7_9_2"
    ],
    "2": [
      "brsurghosp2"
    ],
    "3": [
      "brsurghosp3"
    ],
    "4": [
      "brsurghosp4"
    ]
  },
  "R0_CosmeticOther_Town": {
    "all": [
      "Q7_9_3",
      "brsurgtown2",
      "brsurgtown3",
      "brsurgtown4"
    ],
    "1": [
      "Q7_9_3"
    ],
    "2": [
      "brsurgtown2"
    ],
    "3": [
      "brsurgtown3"
    ],
    "4": [
      "brsurgtown4"
    ]
  },
  "R0_CosmeticOther_Age": {
    "all": [
      "Q7_9_4",
      "brsurgage2",
      "brsurgage3",
      "brsurgage4"
    ],
    "1": [
      "Q7_9_4"
    ],
    "2": [
      "brsurgage2"
    ],
    "3": [
      "brsurgage3"
    ],
    "4": [
      "brsurgage4"
    ]
  },
  "R0_CosmeticOther_Type": {
    "all": [
      "Q7_9_5_1"
    ],
    "1": [
      "Q7_9_5_1"
    ]
  },
  "R0_CosmeticOther_OtherOther": {
    "all": [
      "Q7_9_6",
      "brsurgotherwhat2",
      "brsurgotherwhat3",
      "brsurgotherwhat4"
    ],
    "1": [
      "Q7_9_6"
    ],
    "2": [
      "brsurgotherwhat2"
    ],
    "3": [
      "brsurgotherwhat3"
    ],
    "4": [
      "brsurgotherwhat4"
    ]
  },
  "R0_CosmeticOther_Breast": {
    "all": [
      "Q7_9_7_1",
      "brsurgside2",
      "brsurgside3",
      "brsurgside4"
    ],
    "1": [
      "Q7_9_7_1"
    ],
    "2": [
      "brsurgside2"
    ],
    "3": [
      "brsurgside3"
    ],
    "4": [
      "brsurgside4"
    ]
  },
  "R0_CosmeticOther_Details": {
    "all": [
      "Q7_9_8"
    ]
  },
  "R0_CosmeticOther_Aspiration": {
    "all": [
      "brsurgaspiration2",
      "brsurgaspiration3",
      "brsurgaspiration4"
    ],
    "2": [
      "brsurgaspiration2"
    ],
    "3": [
      "brsurgaspiration3"
    ],
    "4": [
      "brsurgaspiration4"
    ]
  },
  "R0_CosmeticOther_SmallSample": {
    "all": [
      "brsurgbiopsy2",
      "brsurgbiopsy3",
      "brsurgbiopsy4"
    ],
    "2": [
      "brsurgbiopsy2"
    ],
    "3": [
      "brsurgbiopsy3"
    ],
    "4": [
      "brsurgbiopsy4"
    ]
  },
  "R0_CosmeticOther_Enlargement": {
    "all": [
      "brsurgenlarge2",
      "brsurgenlarge3"
    ],
    "2": [
      "brsurgenlarge2"
    ],
    "3": [
      "brsurgenlarge3"
    ]
  },
  "R0_CosmeticOther_Lump": {
    "all": [
      "brsurglumpectomy2",
      "brsurglumpectomy3",
      "brsurglumpectomy4"
    ],
    "2": [
      "brsurglumpectomy2"
    ],
    "3": [
      "brsurglumpectomy3"
    ],
    "4": [
      "brsurglumpectomy4"
    ]
  },
  "R0_CosmeticOther_MoreFour": {
    "all": [
      "brsurgmorex"
    ]
  },
  "R0_CosmeticOther_Mnth": {
    "all": [
      "brsurgmth2",
      "brsurgmth3",
      "brsurgmth4"
    ],
    "2": [
      "brsurgmth2"
    ],
    "3": [
      "brsurgmth3"
    ],
    "4": [
      "brsurgmth4"
    ]
  },
  "R0_CosmeticOther_Other": {
    "all": [
      "brsurgother2",
      "brsurgother3",
      "brsurgother4"
    ],
    "2": [
      "brsurgother2"
    ],
    "3": [
      "brsurgother3"
    ],
    "4": [
      "brsurgother4"
    ]
  },
  "R0_CosmeticOther_Reduction": {
    "all": [
      "brsurgreduction2",
      "brsurgreduction4"
    ],
    "2": [
      "brsurgreduction2"
    ],
    "4": [
      "brsurgreduction4"
    ]
  },
  "R0_CosmeticOther_Yr": {
    "all": [
      "brsurgyr2",
      "brsurgyr3",
      "brsurgyr4"
    ],
    "2": [
      "brsurgyr2"
    ],
    "3": [
      "brsurgyr3"
    ],
    "4": [
      "brsurgyr4"
    ]
  }
}